OneEuroFilter/OneEuroFilter.py
OneEuroFilter/__init__.py
OneEuroFilter-0.2.1.dist-info/LICENSE
OneEuroFilter-0.2.1.dist-info/METADATA
OneEuroFilter-0.2.1.dist-info/WHEEL
OneEuroFilter-0.2.1.dist-info/top_level.txt
OneEuroFilter-0.2.1.dist-info/RECORD
