Metadata-Version: 2.1
Name: OneEuroFilter
Version: 0.2.1
Summary: 1€ filter (One Euro Filter)
Author-email: Géry Casiez <gery.casiez@gmail.com>
Project-URL: Repository, https://github.com/casiez/OneEuroFilter/python
Classifier: Programming Language :: Python :: 3
Classifier: License :: OSI Approved :: BSD License
License-File: LICENSE
